PyFiberModes/__future__.py
PyFiberModes/__init__.py
PyFiberModes/_version.py
PyFiberModes/coordinates.py
PyFiberModes/directories.py
PyFiberModes/factory.py
PyFiberModes/fiber.py
PyFiberModes/field.py
PyFiberModes/fundamentals.py
PyFiberModes/loader.py
PyFiberModes/mode.py
PyFiberModes/mode_instances.py
PyFiberModes/source.py
PyFiberModes/stepindex.py
PyFiberModes/fiber_files/1550BHP.yaml
PyFiberModes/fiber_files/DCF13.yaml
PyFiberModes/fiber_files/DCF1300S_20.yaml
PyFiberModes/fiber_files/DCF1300S_26.yaml
PyFiberModes/fiber_files/DCF1300S_33.yaml
PyFiberModes/fiber_files/DCF1300S_42.yaml
PyFiberModes/fiber_files/F2028M12.yaml
PyFiberModes/fiber_files/F2028M21.yaml
PyFiberModes/fiber_files/F2028M24.yaml
PyFiberModes/fiber_files/F2058G1.yaml
PyFiberModes/fiber_files/F2058L1.yaml
PyFiberModes/fiber_files/HI1060.yaml
PyFiberModes/fiber_files/HP630.yaml
PyFiberModes/fiber_files/SM1950.yaml
PyFiberModes/fiber_files/SMF28.yaml
PyFiberModes/fiber_files/fluorine_doped_1%_capillary.yaml
PyFiberModes/fiber_files/fluorine_doped_2%_capillary.yaml
PyFiberModes/fiber_files/test_fiber.yaml
PyFiberModes/fiber_files/test_multimode_fiber.yaml
PyFiberModes/solver/__init__.py
PyFiberModes/solver/base_solver.py
PyFiberModes/solver/mlsif/__init__.py
PyFiberModes/solver/mlsif/neff.py
PyFiberModes/solver/ssif/__init__.py
PyFiberModes/solver/ssif/cutoff.py
PyFiberModes/solver/ssif/neff.py
PyFiberModes/solver/tlsif/__init__.py
PyFiberModes/solver/tlsif/cutoff.py
PyFiberModes/tools/__init__.py
PyFiberModes/tools/directories.py
PyFiberModes/tools/utils.py
pyfibermodes-0.8.0.dist-info/licenses/LICENSE
pyfibermodes-0.8.0.dist-info/METADATA
pyfibermodes-0.8.0.dist-info/WHEEL
pyfibermodes-0.8.0.dist-info/top_level.txt
pyfibermodes-0.8.0.dist-info/RECORD
