Metadata-Version: 2.4
Name: PyFiberModes
Version: 0.8.0
Summary: A package for light propagation in fiber optics.
Author-email: Martin Poinsinet de Sivry-Houle <martin.poinsinet.de.sivry@gmail.com>
License:                     GNU GENERAL PUBLIC LICENSE
Keywords: finit-difference,matrix
Classifier: Programming Language :: Python
Classifier: Programming Language :: Python :: 3
Classifier: Programming Language :: Python :: 3.11
Classifier: Programming Language :: Python :: 3.12
Classifier: Programming Language :: Python :: Implementation :: CPython
Classifier: Development Status :: 4 - Beta
Classifier: Topic :: Scientific/Engineering :: Physics
Classifier: License :: OSI Approved :: MIT License
Classifier: Intended Audience :: Science/Research
Requires-Python: >=3.10
License-File: LICENSE
Requires-Dist: PyOptik
Requires-Dist: MPSPlots
Requires-Dist: PyFinitDiff
Requires-Dist: pyyaml
Requires-Dist: numpy
Requires-Dist: scipy
Provides-Extra: testing
Requires-Dist: pytest<9.0,>=7.4; extra == "testing"
Requires-Dist: pytest-cov<6,>=2; extra == "testing"
Requires-Dist: pytest-json-report~=1.5; extra == "testing"
Requires-Dist: coverage~=7.6; extra == "testing"
Provides-Extra: documentation
Requires-Dist: numpydoc==1.6.0; extra == "documentation"
Requires-Dist: sphinx>=5.1.1; extra == "documentation"
Requires-Dist: sphinx-gallery==0.15.0; extra == "documentation"
Requires-Dist: sphinx-rtd-theme==2.0.0; extra == "documentation"
Requires-Dist: pydata-sphinx-theme==0.14.1; extra == "documentation"
Provides-Extra: dev
Requires-Dist: flake8==7.1.1; extra == "dev"
Dynamic: license-file
